Metadata-Version: 1.1
Name: laughs
Version: 0.1.2
Summary: Pulls jokes from various APIs
Home-page: https://github.com/seancallaway/laughs
Author: Sean Callaway
Author-email: seancallaway@gmail.com
License: MIT
Platform: UNKNOWN
Classifier: Development Status :: 4 - Beta
Classifier: Programming Language :: Python :: 2.7
Classifier: Programming Language :: Python :: 3.5
Classifier: License :: OSI Approved :: MIT License
Classifier: Topic :: Games/Entertainment :: Fortune Cookies
